README.md
setup.py
nan5_629/__init__.py
nan5_629/core.py
nan5_629.egg-info/PKG-INFO
nan5_629.egg-info/SOURCES.txt
nan5_629.egg-info/dependency_links.txt
nan5_629.egg-info/top_level.txt