Metadata-Version: 2.1
Name: nan5-629
Version: 0.0.1
Summary: 南5舍629的兄弟们 by leigang.
Home-page: https://github.com/leigangblog
Author: leigang
License: MIT
Requires-Python: >=3.6.0
